myblocks/__init__.py
myblocks/blocks.py
myblocks/templates/myblocks/blockquote.html
myblocks/templates/myblocks/embed_block.html
myblocks/templates/myblocks/heading_block.html
myblocks/templates/myblocks/image_block.html
myblocks/templates/myblocks/paragraph_block.html
myblocks/templates/myblocks/recipe_step_block.html
tchappui_myblocks-0.1.1.dist-info/METADATA
tchappui_myblocks-0.1.1.dist-info/WHEEL
tchappui_myblocks-0.1.1.dist-info/RECORD
